{
  "title":{
    "text":"地震专题图",
    "fontSize":50,
    "fontFamily":"STFangsong Regular",
    "fontWeight":"bold",
    "fontColor":"rgba(200,21,17,255)"
  },
  "org":{
    "text":"XX地震局",
    "fontSize":30,
    "fontFamily":"STFangsong Regular",
    "fontWeight":"bold",
    "fontColor":"rgba(100,100,100,255)"
  },
  "date":{
    "prefix":"出图时间 ：",
    "fontSize":30,
    "fontFamily":"STFangsong Regular",
    "fontWeight":"bold",
    "fontColor":"rgba(100,100,100,255)"
  },
  "frame":{
    "width": 1980,
    "height":1400,
    "background":{
      "color":"rgba(255,255,255,255)"
    },
    "frameBackground":{
      "color":"rgba(255,255,227,200)"
    },
    "frameMargin":[30,30,30,30],
    "frameSize":[50,100,50,80],
    "outerBorder":{
      "color":"rgba(0,0,0,255)",
      "width":6
    },
    "innerBorder":{
      "color":"rgba(0,0,0,200)",
      "width":2
    }
  },
  "map":{
    "center"  : [ 103.287496,31.28135 ],
    "zoom"  : 9,
    "crs":"EPSG:3857",
    "layers":[
      {
        "name":"tiandituVec",
        "type":12,
        "url":"http://t{s}.tianditu.cn/DataServer?T=vec_w&X={x}&Y={y}&L={z}",
        "subdomains": ["0", "1", "2", "3", "4", "5", "6", "7"],
        "opacity":1
      },
      {
        "name":"tiandituCva",
        "type":12,
        "url":"http://t{s}.tianditu.cn/DataServer?T=cva_w&X={x}&Y={y}&L={z}",
        "subdomains": ["0", "1", "2", "3", "4", "5", "6", "7"],
        "opacity":1
      }
    ]
  },
  "testData":true
}